README.md
setup.py
animals_templates/__init__.py
animals_templates/bat.py
animals_templates/camel.py
animals_templates/deer.py
animals_templates/goose.py
animals_templates/lion.py
animals_templates/rabbit.py
animals_templates/selectors.py
animals_templates.egg-info/PKG-INFO
animals_templates.egg-info/SOURCES.txt
animals_templates.egg-info/dependency_links.txt
animals_templates.egg-info/top_level.txt