Metadata-Version: 2.1
Name: animals-templates
Version: 0.0.1
Summary: A small package to reuse animals templates
Home-page: https://github.com/tamkovich/animals.git
Author: Denis Tamkovich
Author-email: tamkovichdenis@gmail.com
License: UNKNOWN
Platform: UNKNOWN
Classifier: Programming Language :: Python :: 3
Classifier: License :: OSI Approved :: MIT License
Classifier: Operating System :: OS Independent
